manx/__init__.py
manx/configs.py
manx/exceptions.py
manx/files.py
manx/metadata.py
manx/migrate.py
manx/py.typed
manx-0.3.7.dist-info/LICENSE
manx-0.3.7.dist-info/WHEEL
manx-0.3.7.dist-info/METADATA
manx-0.3.7.dist-info/RECORD
