Metadata-Version: 2.1
Name: manx
Version: 0.3.7
Summary: Data migrations for elasticsearch
Home-page: https://dev.azure.com/convergys-cx/CXS/_git/manx
Author: Eric Grunzke
Author-email: Eric.Grunzke@concentrix.com
Requires-Python: >=3.8,<4.0
Classifier: Programming Language :: Python :: 3
Classifier: Programming Language :: Python :: 3.8
Classifier: Programming Language :: Python :: 3.9
Classifier: Programming Language :: Python :: 3.10
Requires-Dist: elasticsearch[async] (>=7.16.1,<8.0.0)
Project-URL: Repository, https://dev.azure.com/convergys-cx/CXS/_git/manx
